{
  "symbol": "APLY",
  "name": "YieldMax™ AAPLOption Income Strategy ETF",
  "group": "GroupA",
  "frequency": "monthly",
  "events": [
    {
      "symbol": "APLY",
      "exDate": "2025-09-25T00:00:00Z",
      "payDate": "2025-09-26T00:00:00Z",
      "declareDate": "0001-01-01T00:00:00Z",
      "amount": 0.3569,
      "group": "",
      "frequency": ""
    },
    {
      "symbol": "APLY",
      "exDate": "2025-08-28T00:00:00Z",
      "payDate": "2025-08-29T00:00:00Z",
      "declareDate": "0001-01-01T00:00:00Z",
      "amount": 0.3465,
      "group": "",
      "frequency": ""
    },
    {
      "symbol": "APLY",
      "exDate": "2025-07-31T00:00:00Z",
      "payDate": "2025-08-01T00:00:00Z",
      "declareDate": "0001-01-01T00:00:00Z",
      "amount": 0.4103,
      "group": "",
      "frequency": ""
    },
    {
      "symbol": "APLY",
      "exDate": "2025-07-03T00:00:00Z",
      "payDate": "2025-07-04T00:00:00Z",
      "declareDate": "0001-01-01T00:00:00Z",
      "amount": 0.2695,
      "group": "",
      "frequency": ""
    },
    {
      "symbol": "APLY",
      "exDate": "2025-06-05T00:00:00Z",
      "payDate": "2025-06-06T00:00:00Z",
      "declareDate": "0001-01-01T00:00:00Z",
      "amount": 0.3119,
      "group": "",
      "frequency": ""
    },
    {
      "symbol": "APLY",
      "exDate": "2025-05-08T00:00:00Z",
      "payDate": "2025-05-09T00:00:00Z",
      "declareDate": "0001-01-01T00:00:00Z",
      "amount": 0.6512,
      "group": "",
      "frequency": ""
    },
    {
      "symbol": "APLY",
      "exDate": "2025-04-10T00:00:00Z",
      "payDate": "2025-04-11T00:00:00Z",
      "declareDate": "0001-01-01T00:00:00Z",
      "amount": 0.3023,
      "group": "",
      "frequency": ""
    },
    {
      "symbol": "APLY",
      "exDate": "2025-03-13T00:00:00Z",
      "payDate": "2025-03-14T00:00:00Z",
      "declareDate": "0001-01-01T00:00:00Z",
      "amount": 0.344,
      "group": "",
      "frequency": ""
    },
    {
      "symbol": "APLY",
      "exDate": "2025-02-13T00:00:00Z",
      "payDate": "2025-02-14T00:00:00Z",
      "declareDate": "0001-01-01T00:00:00Z",
      "amount": 0.3625,
      "group": "",
      "frequency": ""
    },
    {
      "symbol": "APLY",
      "exDate": "2025-01-16T00:00:00Z",
      "payDate": "2025-01-17T00:00:00Z",
      "declareDate": "0001-01-01T00:00:00Z",
      "amount": 0.2841,
      "group": "",
      "frequency": ""
    },
    {
      "symbol": "APLY",
      "exDate": "2024-12-19T00:00:00Z",
      "payDate": "2024-12-20T00:00:00Z",
      "declareDate": "0001-01-01T00:00:00Z",
      "amount": 0.4215,
      "group": "",
      "frequency": ""
    },
    {
      "symbol": "APLY",
      "exDate": "2024-11-21T00:00:00Z",
      "payDate": "2024-11-22T00:00:00Z",
      "declareDate": "0001-01-01T00:00:00Z",
      "amount": 0.3348,
      "group": "",
      "frequency": ""
    },
    {
      "symbol": "APLY",
      "exDate": "2024-10-24T00:00:00Z",
      "payDate": "2024-10-25T00:00:00Z",
      "declareDate": "0001-01-01T00:00:00Z",
      "amount": 0.3428,
      "group": "",
      "frequency": ""
    },
    {
      "symbol": "APLY",
      "exDate": "2024-09-06T00:00:00Z",
      "payDate": "2024-09-07T00:00:00Z",
      "declareDate": "0001-01-01T00:00:00Z",
      "amount": 0.4525,
      "group": "",
      "frequency": ""
    },
    {
      "symbol": "APLY",
      "exDate": "2024-08-07T00:00:00Z",
      "payDate": "2024-08-08T00:00:00Z",
      "declareDate": "0001-01-01T00:00:00Z",
      "amount": 0.3498,
      "group": "",
      "frequency": ""
    },
    {
      "symbol": "APLY",
      "exDate": "2024-07-05T00:00:00Z",
      "payDate": "2024-07-06T00:00:00Z",
      "declareDate": "0001-01-01T00:00:00Z",
      "amount": 0.3233,
      "group": "",
      "frequency": ""
    },
    {
      "symbol": "APLY",
      "exDate": "2024-06-06T00:00:00Z",
      "payDate": "2024-06-07T00:00:00Z",
      "declareDate": "0001-01-01T00:00:00Z",
      "amount": 0.4043,
      "group": "",
      "frequency": ""
    },
    {
      "symbol": "APLY",
      "exDate": "2024-05-06T00:00:00Z",
      "payDate": "2024-05-07T00:00:00Z",
      "declareDate": "0001-01-01T00:00:00Z",
      "amount": 0.3389,
      "group": "",
      "frequency": ""
    },
    {
      "symbol": "APLY",
      "exDate": "2024-04-04T00:00:00Z",
      "payDate": "2024-04-05T00:00:00Z",
      "declareDate": "0001-01-01T00:00:00Z",
      "amount": 0.3835,
      "group": "",
      "frequency": ""
    },
    {
      "symbol": "APLY",
      "exDate": "2024-03-06T00:00:00Z",
      "payDate": "2024-03-07T00:00:00Z",
      "declareDate": "0001-01-01T00:00:00Z",
      "amount": 0.4158,
      "group": "",
      "frequency": ""
    },
    {
      "symbol": "APLY",
      "exDate": "2024-02-07T00:00:00Z",
      "payDate": "2024-02-08T00:00:00Z",
      "declareDate": "0001-01-01T00:00:00Z",
      "amount": 0.1727,
      "group": "",
      "frequency": ""
    },
    {
      "symbol": "APLY",
      "exDate": "2024-01-05T00:00:00Z",
      "payDate": "2024-01-06T00:00:00Z",
      "declareDate": "0001-01-01T00:00:00Z",
      "amount": 0.5604,
      "group": "",
      "frequency": ""
    },
    {
      "symbol": "APLY",
      "exDate": "2023-12-07T00:00:00Z",
      "payDate": "2023-12-08T00:00:00Z",
      "declareDate": "0001-01-01T00:00:00Z",
      "amount": 0.4658,
      "group": "",
      "frequency": ""
    },
    {
      "symbol": "APLY",
      "exDate": "2023-11-08T00:00:00Z",
      "payDate": "2023-11-09T00:00:00Z",
      "declareDate": "0001-01-01T00:00:00Z",
      "amount": 0.1734,
      "group": "",
      "frequency": ""
    },
    {
      "symbol": "APLY",
      "exDate": "2023-10-06T00:00:00Z",
      "payDate": "2023-10-07T00:00:00Z",
      "declareDate": "0001-01-01T00:00:00Z",
      "amount": 0.4779,
      "group": "",
      "frequency": ""
    },
    {
      "symbol": "APLY",
      "exDate": "2023-09-08T00:00:00Z",
      "payDate": "2023-09-09T00:00:00Z",
      "declareDate": "0001-01-01T00:00:00Z",
      "amount": 0.2256,
      "group": "",
      "frequency": ""
    },
    {
      "symbol": "APLY",
      "exDate": "2023-08-04T00:00:00Z",
      "payDate": "2023-08-05T00:00:00Z",
      "declareDate": "0001-01-01T00:00:00Z",
      "amount": 0.5555,
      "group": "",
      "frequency": ""
    },
    {
      "symbol": "APLY",
      "exDate": "2023-07-07T00:00:00Z",
      "payDate": "2023-07-08T00:00:00Z",
      "declareDate": "0001-01-01T00:00:00Z",
      "amount": 0.633,
      "group": "",
      "frequency": ""
    },
    {
      "symbol": "APLY",
      "exDate": "2023-06-07T00:00:00Z",
      "payDate": "2023-06-08T00:00:00Z",
      "declareDate": "0001-01-01T00:00:00Z",
      "amount": 0.288,
      "group": "",
      "frequency": ""
    }
  ],
  "stats": {
    "totalPayments": 29,
    "averageAmount": 0.3778862068965517,
    "lastAmount": 0.3569,
    "yearToDateTotal": 0,
    "trailingYearTotal": 0,
    "changePercent": 0
  },
  "updatedAt": "2025-09-26T15:17:56.581461966Z"
}